{"coherence": 0.08353930424560216, "top_tokens": [["european", "group", "party", "include", "mep", "irish", "behalf", "british", "green", "member"], ["point", "right", "european", "parliament", "council", "political", "member", "state", "country", "president"], ["million", "state", "aid", "ecu", "member", "financial", "rate", "european", "community", "market"], ["training", "education", "work", "vocational", "development", "programme", "school", "new", "system", "social"], ["member", "whereas", "market", "product", "state", "article", "use", "trade", "mark", "community"], ["regulation", "product", "eec", "animal", "council", "milk", "article", "directive", "point", "community"], ["community", "development", "policy", "programme", "project", "point", "state", "area", "social", "member"], ["council", "european", "point", "commission", "proposal", "community", "parliament", "directive", "decision", "regulation"], ["court", "article", "case", "commission", "paragraph", "decision", "first", "judgment", "ecr", "state"], ["european", "community", "europe", "union", "policy", "commission", "social", "country", "member", "council"], ["republic", "european", "agreement", "community", "council", "commission", "decision", "proposal", "article", "part"], ["benefit", "pension", "sickness", "family", "maternity", "allowance", "social", "security", "oldage", "survivor"], ["judge", "law", "court", "university", "european", "general", "advocate", "president", "member", "justice"], ["uijt", "final", "com", "con", "afll", "judg", "pro", "sffn", "per", "dfis"], ["see", "european", "policy", "aid", "economic", "social", "country", "development", "community", "programme"], ["use", "product", "work", "point", "manufacture", "safety", "health", "measure", "equipment", "include"], ["regulation", "eec", "council", "article", "product", "directive", "community", "commission", "whereas", "state"], ["country", "partner", "transparency", "promote", "develop", "qualification", "level", "member", "awareness", "raise"], ["state", "member", "article", "regulation", "person", "eec", "worker", "work", "social", "council"], ["state", "member", "article", "directive", "national", "law", "provision", "community", "treaty", "court"]], "spanish_coherence": 0.061850573013797164, "spanish_top_tokens": [["grupo", "europeo", "partido", "nombre", "democrata", "verde", "europa", "izquierda", "parlamento", "diputado"], ["europeo", "comision", "\u00e9l", "consejo", "parlamento", "politico", "punto", "mas", "union", "miembro"], ["mill\u00f3n", "ayuda", "miembro", "\u00e9l", "comision", "financiero", "mas", "mercado", "europeo", "ecus"], ["formacion", "profesional", "educacion", "trabajo", "programa", "\u00e9l", "empresa", "desarrollo", "social", "europeo"], ["\u00e9l", "miembro", "producto", "dicho", "poder", "articulo", "mercado", "empresa", "apartado", "parte"], ["reglamento", "animal", "articulo", "consejo", "producto", "punto", "cee", "miembro", "comision", "\u00e9l"], ["desarrollo", "\u00e9l", "programa", "comunitario", "comision", "proyecto", "miembro", "mas", "social", "comunidad"], ["comision", "consejo", "europeo", "punto", "relativo", "parlamento", "articulo", "reglamento", "comunidad", "miembro"], ["apartado", "articulo", "tribunal", "comision", "\u00e9l", "sentencia", "primero", "dicho", "rec", "justicia"], ["europeo", "comunidad", "union", "europa", "politico", "comision", "pa\u00eds", "mas", "\u00e9l", "social"], ["republico", "europeo", "comunidad", "consejo", "acuerdo", "comision", "articulo", "relativo", "tratado", "republica"], ["prestaci\u00f3n", "enfermedad", "subsidio", "pa\u00eds", "asociado", "maternidad", "intercambio", "acerca", "desarrollado", "transparencia"], ["juez", "derecho", "tribunal", "general", "universidad", "miembro", "europeo", "abogado", "presidente", "justicia"], ["miembro", "pa\u00eds", "asociado", "caso", "servicio", "intercambio", "transparencia", "acerca", "desarrollado", "academico"], ["europeo", "vear", "vease", "politico", "cooperacion", "pa\u00eds", "desarrollo", "ayuda", "programa", "seguridad"], ["producto", "\u00e9l", "fabricacion", "punto", "trabajo", "poder", "superior", "seguridad", "mas", "actividad"], ["reglamento", "articulo", "consejo", "cee", "ndeg", "producto", "comision", "relativo", "directivo", "\u00e9l"], ["servicio", "miembro", "articulo", "\u00e9l", "prestador", "caso", "pa\u00eds", "actividad", "comision", "apartado"], ["miembro", "articulo", "trabajador", "reglamento", "ndeg", "derecho", "social", "\u00e9l", "dicho", "apartado"], ["miembro", "articulo", "dicho", "apartado", "\u00e9l", "derecho", "nacional", "poder", "directivo", "deber"]], "diversity": 0.54, "spanish_diversity": 0.425, "average_matching": 1.0, "cla": 0.318858764887155, "dataset": "UN_100w", "embedding_method": "Pre-trained embeddings", "model": "GMM", "dataset_length": 19816, "average_document_length": 54.0, "vocab_size": 3996}